bolt_control_flow/__init__.py
bolt_control_flow/helpers.py
bolt_control_flow/modules/test/helpers.bolt
bolt_control_flow/parse.py
bolt_control_flow/py.typed
bolt_control_flow/types.py
bolt_control_flow-0.4.0.dist-info/WHEEL
bolt_control_flow-0.4.0.dist-info/METADATA
bolt_control_flow-0.4.0.dist-info/RECORD
